Workbook
Name AnnualSavings: Assumptions!$C$9
Name CapexY0: Assumptions!$C$11
Name CapexY1: Assumptions!$C$12
Name CO2_kg_per_kgCoal: Assumptions!$C$20
Name Coal_TPH: Assumptions!$C$21
Name Coal_tpy: Assumptions!$C$23
Name DepLife: Assumptions!$C$18
Name DepMethod: Assumptions!$C$17
Name DiscountRate: Assumptions!$C$15
Name HoursPerYear: Assumptions!$C$7
Name InvestmentTotal: Assumptions!$C$14
Name LP_TPD: Assumptions!$C$6
Name OMCost: Assumptions!$C$10
Name ProjectLife: Assumptions!$C$14
Name ResidualValue: Assumptions!$C$19
Name SteamSavings_tpy: Assumptions!$C$9
Name TaxRate: Assumptions!$C$16

Sheet Problem Statement
A1: Case 3 – Flash Steam Recovery (ITC Ltd.)
A3: Ringkasan
A4: Pemulihan flash steam dari blowdown & kondensat SAH untuk memanaskan DM water ke deaerator. Dampak: LP steam ↓ ~19.5 TPD (±6,500 t/yr), investasi ~USD 35k, penghematan ~USD 45,349/yr. Workbook v3 menambahkan: capex bertahap (Y0 & Y1), residual value, 2‑way sensitivity NPV (Rate×Savings), dan tornado chart.
A12: Cara pakai
A13: 1) Masukkan/ubah input di sheet Assumptions (kolom C biru). 2) Financials menghitung arus kas after-tax & KPI. 3) Sensitivity: one‑way (tabel) + tornado. 4) 2‑Way NPV: grid NPV terhadap (Discount Rate × Annual Savings).

Sheet Assumptions
A1: Key Inputs (edit kolom C saja)
A3: Category | B3: Input | C3: Value | D3: Unit / Note
A4: Project | B4: Currency | C4: USD
A5: Project | B5: Analysis start year | C5: 2025
A6: Performance | B6: LP steam reduction (TPD) | C6: 19.5 | D6: Per case study
A7: Performance | B7: Operating hours per year | C7: 8000 | D7: hr/yr
A8: Performance | B8: Steam savings (t/yr) [calc] | C8: =LP_TPD/24*HoursPerYear -> 0 | D8: =TPD/24 * hours -> 0
A9: Economics | B9: Annual gross savings ($/yr) | C9: 45349 | D9: From case study
A10: O&M | B10: Annual O&M cost ($/yr) | C10: 0
A11: Capex | B11: Capex Year 0 ($) | C11: 35000 | D11: Paid at t=0
A12: Capex | B12: Capex Year 1 ($) | C12: 0 | D12: Optional, paid at t=1
A13: Capex | B13: Total Investment [calc] | C13: =CapexY0+CapexY1 -> 0 | D13: =Y0 + Y1 -> 0
A14: Economics | B14: Project life (years) | C14: 10
A15: Economics | B15: Discount rate (WACC) | C15: 0.1
A16: Tax & Depreciation | B16: Corporate tax rate | C16: 0.25
A17: Tax & Depreciation | B17: Depreciation method | C17: Straight-line | D17: Choose "Straight-line" or "WDV 20%"
A18: Tax & Depreciation | B18: Depreciation life (years) | C18: 5 | D18: For Straight-line
A19: End of Life | B19: Residual value ($ at year end) | C19: 0 | D19: Cash inflow at final year (no tax modeled)
A20: Emissions | B20: Coal CO2 factor (kg CO2/kg) | C20: 1.53
A21: Emissions | B21: Coal conserved (TPH) | C21: 0.156 | D21: Per case study
A22: Emissions | B22: Coal conserved (t/yr) [calc] | C22: =Coal_TPH*1000*HoursPerYear -> 0 | D22: =TPH*1000*hours -> 0
A25: Notes:
A26: Edit di kolom C (biru). Total Investment & Steam/Coal calc otomatis.

Sheet Technical Calcs
A1: Technical Calculations
A3: Description | B3: Formula | C3: Result | D3: Unit/Note
A5: Steam savings (t/yr) | B5: =SteamSavings_tpy -> 0 | C5: =SteamSavings_tpy -> 0 | D5: t/yr
A6: Annual hours (hr/yr) | B6: =HoursPerYear -> 0 | C6: =HoursPerYear -> 0 | D6: hr/yr
A7: LP steam reduction (TPD) | B7: =LP_TPD -> 0 | C7: =LP_TPD -> 0 | D7: TPD
A8: Coal conserved (t/yr) | B8: =Coal_tpy -> 0 | C8: =Coal_tpy -> 0 | D8: t/yr
A9: Annual cost savings ($/yr) | B9: =AnnualSavings -> 0 | C9: =AnnualSavings -> 0 | D9: $/yr

Sheet Financials
A1: Financial Model (After-Tax Cash Flows)
A3: Year | B3: Capex ($) | C3: Revenue/Savings ($) | D3: O&M ($) | E3: Depreciation ($) | F3: EBIT ($) | G3: Tax ($) | H3: Net Income ($) | I3: Add-back Depreciation ($) | J3: Free Cash Flow ($) | K3: Discount Factor | L3: PV of FCF ($) | M3: Cumulative PV ($) | N3: Opening Book ($) | O3: Closing Book ($) | P3: Project life (years) | Q3: =ProjectLife -> 0
A4: 0 | B4: =-CapexY0 -> 0 | C4: 0 | D4: 0 | E4: 0 | F4: =(C4-D4-E4) -> 0 | G4: =MAX(F4*TaxRate,0) -> 0 | H4: =F4-G4 -> 0 | I4: =E4 -> 0 | J4: =B4+C4-D4-G4 -> 0 | K4: =1/(1+DiscountRate)^A4 -> 0 | L4: =J4*K4 -> 0 | M4: =SUM(L$4:L4) -> 0 | N4: 0 | O4: =MAX(N4-E4,0) -> 0 | P4: Tax rate | Q4: =TaxRate -> 0
A5: 1 | B5: =-CapexY1 -> 0 | C5: =AnnualSavings -> 0 | D5: =OMCost -> 0 | E5: =IF(DepMethod="Straight-line", IF(AND(A5>0, A5<=DepLife), InvestmentTotal/DepLife, 0), N5*20%) -> 0 | F5: =(C5-D5-E5) -> 0 | G5: =MAX(F5*TaxRate,0) -> 0 | H5: =F5-G5 -> 0 | I5: =E5 -> 0 | J5: =B5+C5-D5-G5 -> 0 | K5: =1/(1+DiscountRate)^A5 -> 0 | L5: =J5*K5 -> 0 | M5: =SUM(L$4:L5) -> 0 | N5: =O4+(-B5) -> 0 | O5: =MAX(N5-E5,0) -> 0 | P5: Discount rate | Q5: =DiscountRate -> 0
A6: 2 | B6: 0 | C6: =AnnualSavings -> 0 | D6: =OMCost -> 0 | E6: =IF(DepMethod="Straight-line", IF(AND(A6>0, A6<=DepLife), InvestmentTotal/DepLife, 0), N6*20%) -> 0 | F6: =(C6-D6-E6) -> 0 | G6: =MAX(F6*TaxRate,0) -> 0 | H6: =F6-G6 -> 0 | I6: =E6 -> 0 | J6: =B6+C6-D6-G6 -> 0 | K6: =1/(1+DiscountRate)^A6 -> 0 | L6: =J6*K6 -> 0 | M6: =SUM(L$4:L6) -> 0 | N6: =O5+(-B6) -> 0 | O6: =MAX(N6-E6,0) -> 0 | P6: Capex Y0 | Q6: =CapexY0 -> 0
A7: 3 | B7: 0 | C7: =AnnualSavings -> 0 | D7: =OMCost -> 0 | E7: =IF(DepMethod="Straight-line", IF(AND(A7>0, A7<=DepLife), InvestmentTotal/DepLife, 0), N7*20%) -> 0 | F7: =(C7-D7-E7) -> 0 | G7: =MAX(F7*TaxRate,0) -> 0 | H7: =F7-G7 -> 0 | I7: =E7 -> 0 | J7: =B7+C7-D7-G7 -> 0 | K7: =1/(1+DiscountRate)^A7 -> 0 | L7: =J7*K7 -> 0 | M7: =SUM(L$4:L7) -> 0 | N7: =O6+(-B7) -> 0 | O7: =MAX(N7-E7,0) -> 0 | P7: Capex Y1 | Q7: =CapexY1 -> 0
A8: 4 | B8: 0 | C8: =AnnualSavings -> 0 | D8: =OMCost -> 0 | E8: =IF(DepMethod="Straight-line", IF(AND(A8>0, A8<=DepLife), InvestmentTotal/DepLife, 0), N8*20%) -> 0 | F8: =(C8-D8-E8) -> 0 | G8: =MAX(F8*TaxRate,0) -> 0 | H8: =F8-G8 -> 0 | I8: =E8 -> 0 | J8: =B8+C8-D8-G8 -> 0 | K8: =1/(1+DiscountRate)^A8 -> 0 | L8: =J8*K8 -> 0 | M8: =SUM(L$4:L8) -> 0 | N8: =O7+(-B8) -> 0 | O8: =MAX(N8-E8,0) -> 0 | P8: Total Investment | Q8: =InvestmentTotal -> 0
A9: 5 | B9: 0 | C9: =AnnualSavings -> 0 | D9: =OMCost -> 0 | E9: =IF(DepMethod="Straight-line", IF(AND(A9>0, A9<=DepLife), InvestmentTotal/DepLife, 0), N9*20%) -> 0 | F9: =(C9-D9-E9) -> 0 | G9: =MAX(F9*TaxRate,0) -> 0 | H9: =F9-G9 -> 0 | I9: =E9 -> 0 | J9: =B9+C9-D9-G9 -> 0 | K9: =1/(1+DiscountRate)^A9 -> 0 | L9: =J9*K9 -> 0 | M9: =SUM(L$4:L9) -> 0 | N9: =O8+(-B9) -> 0 | O9: =MAX(N9-E9,0) -> 0 | P9: Annual savings | Q9: =AnnualSavings -> 0
A10: 6 | B10: 0 | C10: =AnnualSavings -> 0 | D10: =OMCost -> 0 | E10: =IF(DepMethod="Straight-line", IF(AND(A10>0, A10<=DepLife), InvestmentTotal/DepLife, 0), N10*20%) -> 0 | F10: =(C10-D10-E10) -> 0 | G10: =MAX(F10*TaxRate,0) -> 0 | H10: =F10-G10 -> 0 | I10: =E10 -> 0 | J10: =B10+C10-D10-G10 -> 0 | K10: =1/(1+DiscountRate)^A10 -> 0 | L10: =J10*K10 -> 0 | M10: =SUM(L$4:L10) -> 0 | N10: =O9+(-B10) -> 0 | O10: =MAX(N10-E10,0) -> 0 | P10: O&M | Q10: =OMCost -> 0
A11: 7 | B11: 0 | C11: =AnnualSavings -> 0 | D11: =OMCost -> 0 | E11: =IF(DepMethod="Straight-line", IF(AND(A11>0, A11<=DepLife), InvestmentTotal/DepLife, 0), N11*20%) -> 0 | F11: =(C11-D11-E11) -> 0 | G11: =MAX(F11*TaxRate,0) -> 0 | H11: =F11-G11 -> 0 | I11: =E11 -> 0 | J11: =B11+C11-D11-G11 -> 0 | K11: =1/(1+DiscountRate)^A11 -> 0 | L11: =J11*K11 -> 0 | M11: =SUM(L$4:L11) -> 0 | N11: =O10+(-B11) -> 0 | O11: =MAX(N11-E11,0) -> 0 | P11: Dep life (years) | Q11: =DepLife -> 0
A12: 8 | B12: 0 | C12: =AnnualSavings -> 0 | D12: =OMCost -> 0 | E12: =IF(DepMethod="Straight-line", IF(AND(A12>0, A12<=DepLife), InvestmentTotal/DepLife, 0), N12*20%) -> 0 | F12: =(C12-D12-E12) -> 0 | G12: =MAX(F12*TaxRate,0) -> 0 | H12: =F12-G12 -> 0 | I12: =E12 -> 0 | J12: =B12+C12-D12-G12 -> 0 | K12: =1/(1+DiscountRate)^A12 -> 0 | L12: =J12*K12 -> 0 | M12: =SUM(L$4:L12) -> 0 | N12: =O11+(-B12) -> 0 | O12: =MAX(N12-E12,0) -> 0 | P12: Dep method | Q12: =DepMethod -> 0
A13: 9 | B13: 0 | C13: =AnnualSavings -> 0 | D13: =OMCost -> 0 | E13: =IF(DepMethod="Straight-line", IF(AND(A13>0, A13<=DepLife), InvestmentTotal/DepLife, 0), N13*20%) -> 0 | F13: =(C13-D13-E13) -> 0 | G13: =MAX(F13*TaxRate,0) -> 0 | H13: =F13-G13 -> 0 | I13: =E13 -> 0 | J13: =B13+C13-D13-G13 -> 0 | K13: =1/(1+DiscountRate)^A13 -> 0 | L13: =J13*K13 -> 0 | M13: =SUM(L$4:L13) -> 0 | N13: =O12+(-B13) -> 0 | O13: =MAX(N13-E13,0) -> 0 | P13: Residual value (final year) | Q13: =ResidualValue -> 0
A14: 10 | B14: 0 | C14: =AnnualSavings -> 0 | D14: =OMCost -> 0 | E14: =IF(DepMethod="Straight-line", IF(AND(A14>0, A14<=DepLife), InvestmentTotal/DepLife, 0), N14*20%) -> 0 | F14: =(C14-D14-E14) -> 0 | G14: =MAX(F14*TaxRate,0) -> 0 | H14: =F14-G14 -> 0 | I14: =E14 -> 0 | J14: =B14+C14-D14-G14+ResidualValue -> 0 | K14: =1/(1+DiscountRate)^A14 -> 0 | L14: =J14*K14 -> 0 | M14: =SUM(L$4:L14) -> 0 | N14: =O13+(-B14) -> 0 | O14: =MAX(N14-E14,0) -> 0
N16: KPIs
N17: NPV ($) | O17: =SUM(L4:L15) -> 0
N18: IRR (%) | O18: =IRR(J4:J15) -> 0
N19: Simple Payback (yrs) | O19: =IFERROR(MATCH(TRUE,INDEX(M4:M15>0,0),0)-1,"") -> 0
N20: Discounted Payback (yrs) | O20: =IFERROR(MATCH(TRUE,INDEX(M4:M15>0,0),0)-1,"") -> 0

Sheet Sensitivity
A1: One‑Way Sensitivity & Tornado
A3: Variable | B3: Low | C3: Base | D3: High | E3: NPV@Low | F3: NPV@Base | G3: NPV@High
A5: Discount rate | B5: 0.08 | C5: =DiscountRate -> 0 | D5: 0.15 | E5: =NPV(B5,Financials!J5:J15)+Financials!J4 -> 0 | F5: =NPV(C5,Financials!J5:J15)+Financials!J4 -> 0 | G5: =NPV(D5,Financials!J5:J15)+Financials!J4 -> 0
A6: Investment ($) | B6: 30000 | C6: =InvestmentTotal -> 0 | D6: 45000 | E6: =NPV(DiscountRate,Financials!J5:J15)+(-B6) -> 0 | F6: =NPV(DiscountRate,Financials!J5:J15)+(-C6) -> 0 | G6: =NPV(DiscountRate,Financials!J5:J15)+(-D6) -> 0
A7: Annual savings ($/yr) | B7: 40000 | C7: =AnnualSavings -> 0 | D7: 50000 | E7: =NPV(DiscountRate,Financials!J5:J15)+Financials!J4 + (B7-AnnualSavings)*(1-TaxRate)*( (1-(1+DiscountRate)^-ProjectLife)/DiscountRate ) -> 0 | F7: =NPV(DiscountRate,Financials!J5:J15)+Financials!J4 -> 0 | G7: =NPV(DiscountRate,Financials!J5:J15)+Financials!J4 + (D7-AnnualSavings)*(1-TaxRate)*( (1-(1+DiscountRate)^-ProjectLife)/DiscountRate ) -> 0
A9: Tornado Inputs
A10: Variable | B10: ΔNPV Low vs Base | C10: ΔNPV High vs Base
A12: =A4 -> 0 | B12: =E4-F4 -> 0 | C12: =G4-F4 -> 0
A13: =A5 -> 0 | B13: =E5-F5 -> 0 | C13: =G5-F5 -> 0
A14: =A6 -> 0 | B14: =E6-F6 -> 0 | C14: =G6-F6 -> 0

Sheet 2‑Way NPV
A1: NPV Grid: Discount Rate × Annual Savings
A3: Rates → (rows) | Savings → (columns)
A5: Rate \ Savings | B5: 38000 | C5: 42000 | D5: 45349 | E5: 48000 | F5: 52000
A6: 0.06 | B6: =NPV($A$6,Financials!J5:J15)+Financials!J4 + ($B$5-AnnualSavings)*(1-TaxRate)*((1-(1+$A$6)^-ProjectLife)/$A$6) -> 0 | C6: =NPV($A$6,Financials!J5:J15)+Financials!J4 + ($C$5-AnnualSavings)*(1-TaxRate)*((1-(1+$A$6)^-ProjectLife)/$A$6) -> 0 | D6: =NPV($A$6,Financials!J5:J15)+Financials!J4 + ($D$5-AnnualSavings)*(1-TaxRate)*((1-(1+$A$6)^-ProjectLife)/$A$6) -> 0 | E6: =NPV($A$6,Financials!J5:J15)+Financials!J4 + ($E$5-AnnualSavings)*(1-TaxRate)*((1-(1+$A$6)^-ProjectLife)/$A$6) -> 0 | F6: =NPV($A$6,Financials!J5:J15)+Financials!J4 + ($F$5-AnnualSavings)*(1-TaxRate)*((1-(1+$A$6)^-ProjectLife)/$A$6) -> 0
A7: 0.08 | B7: =NPV($A$7,Financials!J5:J15)+Financials!J4 + ($B$5-AnnualSavings)*(1-TaxRate)*((1-(1+$A$7)^-ProjectLife)/$A$7) -> 0 | C7: =NPV($A$7,Financials!J5:J15)+Financials!J4 + ($C$5-AnnualSavings)*(1-TaxRate)*((1-(1+$A$7)^-ProjectLife)/$A$7) -> 0 | D7: =NPV($A$7,Financials!J5:J15)+Financials!J4 + ($D$5-AnnualSavings)*(1-TaxRate)*((1-(1+$A$7)^-ProjectLife)/$A$7) -> 0 | E7: =NPV($A$7,Financials!J5:J15)+Financials!J4 + ($E$5-AnnualSavings)*(1-TaxRate)*((1-(1+$A$7)^-ProjectLife)/$A$7) -> 0 | F7: =NPV($A$7,Financials!J5:J15)+Financials!J4 + ($F$5-AnnualSavings)*(1-TaxRate)*((1-(1+$A$7)^-ProjectLife)/$A$7) -> 0
A8: 0.1 | B8: =NPV($A$8,Financials!J5:J15)+Financials!J4 + ($B$5-AnnualSavings)*(1-TaxRate)*((1-(1+$A$8)^-ProjectLife)/$A$8) -> 0 | C8: =NPV($A$8,Financials!J5:J15)+Financials!J4 + ($C$5-AnnualSavings)*(1-TaxRate)*((1-(1+$A$8)^-ProjectLife)/$A$8) -> 0 | D8: =NPV($A$8,Financials!J5:J15)+Financials!J4 + ($D$5-AnnualSavings)*(1-TaxRate)*((1-(1+$A$8)^-ProjectLife)/$A$8) -> 0 | E8: =NPV($A$8,Financials!J5:J15)+Financials!J4 + ($E$5-AnnualSavings)*(1-TaxRate)*((1-(1+$A$8)^-ProjectLife)/$A$8) -> 0 | F8: =NPV($A$8,Financials!J5:J15)+Financials!J4 + ($F$5-AnnualSavings)*(1-TaxRate)*((1-(1+$A$8)^-ProjectLife)/$A$8) -> 0
A9: 0.12 | B9: =NPV($A$9,Financials!J5:J15)+Financials!J4 + ($B$5-AnnualSavings)*(1-TaxRate)*((1-(1+$A$9)^-ProjectLife)/$A$9) -> 0 | C9: =NPV($A$9,Financials!J5:J15)+Financials!J4 + ($C$5-AnnualSavings)*(1-TaxRate)*((1-(1+$A$9)^-ProjectLife)/$A$9) -> 0 | D9: =NPV($A$9,Financials!J5:J15)+Financials!J4 + ($D$5-AnnualSavings)*(1-TaxRate)*((1-(1+$A$9)^-ProjectLife)/$A$9) -> 0 | E9: =NPV($A$9,Financials!J5:J15)+Financials!J4 + ($E$5-AnnualSavings)*(1-TaxRate)*((1-(1+$A$9)^-ProjectLife)/$A$9) -> 0 | F9: =NPV($A$9,Financials!J5:J15)+Financials!J4 + ($F$5-AnnualSavings)*(1-TaxRate)*((1-(1+$A$9)^-ProjectLife)/$A$9) -> 0
A10: 0.15 | B10: =NPV($A$10,Financials!J5:J15)+Financials!J4 + ($B$5-AnnualSavings)*(1-TaxRate)*((1-(1+$A$10)^-ProjectLife)/$A$10) -> 0 | C10: =NPV($A$10,Financials!J5:J15)+Financials!J4 + ($C$5-AnnualSavings)*(1-TaxRate)*((1-(1+$A$10)^-ProjectLife)/$A$10) -> 0 | D10: =NPV($A$10,Financials!J5:J15)+Financials!J4 + ($D$5-AnnualSavings)*(1-TaxRate)*((1-(1+$A$10)^-ProjectLife)/$A$10) -> 0 | E10: =NPV($A$10,Financials!J5:J15)+Financials!J4 + ($E$5-AnnualSavings)*(1-TaxRate)*((1-(1+$A$10)^-ProjectLife)/$A$10) -> 0 | F10: =NPV($A$10,Financials!J5:J15)+Financials!J4 + ($F$5-AnnualSavings)*(1-TaxRate)*((1-(1+$A$10)^-ProjectLife)/$A$10) -> 0

Sheet GHG Impact
A1: Greenhouse Gas Impact
A3: Metric | B3: Formula | C3: Result | D3: Unit/Note
A4: Coal conserved (t/yr) | B4: =Coal_tpy -> 0 | C4: =B4 -> 0 | D4: t/yr
A5: CO2 factor (tCO2/t coal) | B5: =CO2_kg_per_kgCoal/1000 -> 0 | C5: =B5 -> 0 | D5: tCO2/t coal
A6: Annual CO2 avoided (tCO2/yr) | B6: =C4*C5 -> 0 | C6: =B6 -> 0 | D6: Indicative ~1.9 ktCO2/yr

Sheet Summary
A1: Project Dashboard
A3: KPI | B3: Value | C3: Unit
A5: Total Investment | B5: =InvestmentTotal -> 0 | C5: $
A6: Annual savings | B6: =AnnualSavings -> 0 | C6: $/yr
A7: NPV | B7: =SUM(Financials!L4:L15) -> 0 | C7: $
A8: IRR | B8: =IRR(Financials!J4:J15) -> 0 | C8: %
A9: Simple Payback | B9: =IFERROR(InvestmentTotal/AnnualSavings,"") -> 0 | C9: years
A10: Steam savings | B10: =SteamSavings_tpy -> 0 | C10: t/yr
A11: CO2 avoided | B11: =GHG Impact!C6 -> 0 | C11: tCO2/yr
